Metadata-Version: 2.2
Name: com.castsoftware.uc.python.common
Version: 1.2.0
Summary: A set of common classes and methods for use with python projects
Project-URL: Homepage, https://github.com/CAST-Extend/com.castsoftware.uc.python.common
Project-URL: Bug Tracker, https://github.com/CAST-Extend/com.castsoftware.uc.python.common/issues
Classifier: Programming Language :: Python :: 3
Classifier: License :: OSI Approved :: GNU General Public License v3 (GPLv3)
Classifier: Operating System :: OS Independent
Requires-Python: >=3.10.6
License-File: LICENSE
Requires-Dist: pandas
Requires-Dist: requests
Requires-Dist: XlsxWriter
Requires-Dist: tqdm
Requires-Dist: inquirer
Requires-Dist: python-pptx==0.6.21
